{
    "schema_version": "1",
    "id": "renewed-energy",
    "title": "Renewed Energy",
    "artist_id": "brylie-christopher",
    "release_type": "album",
    "status": "live",
    "license": "CC BY 4.0",
    "description": {
        "short": "Inspired by sources from sunshine to centering prayer that breathe life into our being.",
        "full": "Inspired by sources from sunshine to centering prayer that breathe life into our being."
    },
    "genre_tags": [
        "electronic",
        "ambient",
        "experimental"
    ],
    "dates": {
        "released": "2023-10-22"
    },
    "store_links": {
        "soundcloud": "https://soundcloud.com/brylie/sets/renewed-energy",
        "bandcamp": "https://brylie.bandcamp.com/album/renewed-energy",
        "apple_music": "https://music.apple.com/fi/album/renewed-energy/1715833322",
        "spotify": "https://open.spotify.com/album/5ZFnigyZigvyH2W2jBFxDu",
        "fma": "https://freemusicarchive.org/music/Brylie_Christopher_Oxley/renewed-energy",
        "subvert_fm": "https://www.subvert.fm/brylie/renewed-energy"
    },
    "created_date": "2026-06-19"
}